exstats/__init__.py
exstats-1.2.0.dist-info/METADATA
exstats-1.2.0.dist-info/WHEEL
exstats-1.2.0.dist-info/top_level.txt
exstats-1.2.0.dist-info/RECORD
